[
  {
    "id": 1,
    "message": "Buat yang suka duduk di pojok kanan kelas SI-3A, semangat ya skripsinya! Aku diem-diem ngefans lho.",
    "color": "bg-gradient-to-br from-pink-100 to-rose-200 text-rose-800"
  },
  {
    "id": 2,
    "message": "Terima kasih buat Dosen Alpro yang udah kasih nilai A, meskipun kodingan saya copas StackOverflow semua.",
    "color": "bg-gradient-to-br from-blue-100 to-cyan-200 text-blue-800"
  },
  {
    "id": 3,
    "message": "Maaf ya pulpen kalian sering ilang, sebenernya kebawa aku ke kosan... numpuk jadi koleksi.",
    "color": "bg-gradient-to-br from-yellow-100 to-amber-200 text-amber-800"
  },
  {
    "id": 4,
    "message": "Guys, jangan lupa bayar uang kas. Bendahara udah mode maung tuh.",
    "color": "bg-gradient-to-br from-green-100 to-emerald-200 text-emerald-800"
  },
  {
    "id": 5,
    "message": "Semoga kita semua lulus bareng tepat waktu! Aamiin!",
    "color": "bg-gradient-to-br from-purple-100 to-violet-200 text-purple-800"
  },
  {
    "id": 6,
    "message": "Cie yang kemarin ketahuan jalan bareng anak DKV di kantin...",
    "color": "bg-gradient-to-br from-orange-100 to-red-200 text-red-800"
  },
  {
    "id": 7,
    "message": "Info loker: Mencari jodoh yang bisa bantuin ngoding React JS.",
    "color": "bg-gradient-to-br from-gray-100 to-slate-300 text-slate-800"
  }
]